ol_openedx_canvas_integration/__init__.py
ol_openedx_canvas_integration/api.py
ol_openedx_canvas_integration/app.py
ol_openedx_canvas_integration/client.py
ol_openedx_canvas_integration/cms_tasks.py
ol_openedx_canvas_integration/constants.py
ol_openedx_canvas_integration/context_api.py
ol_openedx_canvas_integration/handlers.py
ol_openedx_canvas_integration/receivers.py
ol_openedx_canvas_integration/task_helpers.py
ol_openedx_canvas_integration/tasks.py
ol_openedx_canvas_integration/urls.py
ol_openedx_canvas_integration/utils.py
ol_openedx_canvas_integration/views.py
ol_openedx_canvas_integration/settings/__init__.py
ol_openedx_canvas_integration/settings/common.py
ol_openedx_canvas_integration/settings/production.py
ol_openedx_canvas_integration/static/js/canvas_integration.js
ol_openedx_canvas_integration/templates/canvas_integration.html
ol_openedx_canvas_integration-0.6.0.dist-info/METADATA
ol_openedx_canvas_integration-0.6.0.dist-info/WHEEL
ol_openedx_canvas_integration-0.6.0.dist-info/entry_points.txt
ol_openedx_canvas_integration-0.6.0.dist-info/licenses/LICENSE.txt
ol_openedx_canvas_integration-0.6.0.dist-info/RECORD
